DendroPy_calver-2023.330.2.data/scripts/dendropy-format
DendroPy_calver-2023.330.2.data/scripts/sumlabels.py
DendroPy_calver-2023.330.2.data/scripts/sumtrees.py
dendropy/__init__.py
dendropy/__main__.py
dendropy/calculate/__init__.py
dendropy/calculate/combinatorics.py
dendropy/calculate/mathfn.py
dendropy/calculate/phylogeneticdistance.py
dendropy/calculate/popgenstat.py
dendropy/calculate/probability.py
dendropy/calculate/profiledistance.py
dendropy/calculate/statistics.py
dendropy/calculate/treecompare.py
dendropy/calculate/treemeasure.py
dendropy/calculate/treescore.py
dendropy/calculate/treesum.py
dendropy/dataio/__init__.py
dendropy/dataio/fastareader.py
dendropy/dataio/fastawriter.py
dendropy/dataio/ioservice.py
dendropy/dataio/multiphylipreader.py
dendropy/dataio/newick.py
dendropy/dataio/newickreader.py
dendropy/dataio/newickwriter.py
dendropy/dataio/newickyielder.py
dendropy/dataio/nexmlreader.py
dendropy/dataio/nexmlwriter.py
dendropy/dataio/nexmlyielder.py
dendropy/dataio/nexusprocessing.py
dendropy/dataio/nexusreader.py
dendropy/dataio/nexuswriter.py
dendropy/dataio/nexusyielder.py
dendropy/dataio/phylipreader.py
dendropy/dataio/phylipwriter.py
dendropy/dataio/tokenizer.py
dendropy/dataio/xmlprocessing.py
dendropy/datamodel/__init__.py
dendropy/datamodel/basemodel.py
dendropy/datamodel/charmatrixmodel.py
dendropy/datamodel/charstatemodel.py
dendropy/datamodel/datasetmodel.py
dendropy/datamodel/taxonmodel.py
dendropy/datamodel/treecollectionmodel.py
dendropy/datamodel/treemodel/__init__.py
dendropy/datamodel/treemodel/_bipartition.py
dendropy/datamodel/treemodel/_edge.py
dendropy/datamodel/treemodel/_node.py
dendropy/datamodel/treemodel/_tree.py
dendropy/interop/__init__.py
dendropy/interop/ape.py
dendropy/interop/biopython.py
dendropy/interop/entrez.py
dendropy/interop/ete.py
dendropy/interop/gbif.py
dendropy/interop/genbank.py
dendropy/interop/itol.py
dendropy/interop/muscle.py
dendropy/interop/paup.py
dendropy/interop/raxml.py
DendroPy_calver-2023.330.2.dist-info/AUTHORS.rst
DendroPy_calver-2023.330.2.dist-info/LICENSE.rst
DendroPy_calver-2023.330.2.dist-info/METADATA
DendroPy_calver-2023.330.2.dist-info/WHEEL
DendroPy_calver-2023.330.2.dist-info/entry_points.txt
DendroPy_calver-2023.330.2.dist-info/top_level.txt
DendroPy_calver-2023.330.2.dist-info/zip-safe
DendroPy_calver-2023.330.2.dist-info/RECORD
