Metadata-Version: 2.1
Name: DendroPy-calver
Version: 2023.330.2
Summary: A Python library for phylogenetics and phylogenetic computing: reading, writing, simulation, processing and manipulation of phylogenetic trees (phylogenies) and characters. Calendar-versioned fork tracking DendroPy main branch.
Home-page: http://github.com/mmore500/DendroPy/
Author: forked by Matthew Andres Moreno from Jeet Sukumaran and Mark T. Holder
Author-email: m.more500@gmail.com, jeetsukumaran@gmail.com, mtholder@ku.edu
License: BSD
Keywords: phylogenetics phylogeny phylogenies phylogeography evolution evolutionary biology systematics coalescent population genetics phyloinformatics bioinformatics
Platform: UNKNOWN
Classifier: Intended Audience :: Developers
Classifier: Intended Audience :: Science/Research
Classifier: License :: OSI Approved :: BSD License
Classifier: Natural Language :: English
Classifier: Operating System :: OS Independent
Classifier: Programming Language :: Python :: 2.7
Classifier: Programming Language :: Python :: 3
Classifier: Programming Language :: Python :: 3.1
Classifier: Programming Language :: Python :: 3.2
Classifier: Programming Language :: Python :: 3.3
Classifier: Programming Language :: Python :: 3.4
Classifier: Programming Language :: Python :: 3.5
Classifier: Programming Language :: Python :: 3.6
Classifier: Programming Language :: Python :: 3.7
Classifier: Programming Language :: Python :: 3.8
Classifier: Programming Language :: Python
Classifier: Topic :: Scientific/Engineering :: Bio-Informatics
Requires-Dist: setuptools
